dddpy/__init__.py
dddpy/bases/__init__.py
dddpy/bases/common/__init__.py
dddpy/bases/common/abstract.py
dddpy/bases/common/primitive.py
dddpy/bases/domain/__init__.py
dddpy-0.5.1.dist-info/LICENSE
dddpy-0.5.1.dist-info/WHEEL
dddpy-0.5.1.dist-info/METADATA
dddpy-0.5.1.dist-info/RECORD
